jsonschema-stubs/METADATA.toml
jsonschema-stubs/__init__.pyi
jsonschema-stubs/_format.pyi
jsonschema-stubs/_keywords.pyi
jsonschema-stubs/_legacy_keywords.pyi
jsonschema-stubs/_types.pyi
jsonschema-stubs/_typing.pyi
jsonschema-stubs/_utils.pyi
jsonschema-stubs/cli.pyi
jsonschema-stubs/exceptions.pyi
jsonschema-stubs/protocols.pyi
jsonschema-stubs/py.typed
jsonschema-stubs/validators.pyi
types_jsonschema-4.26.0.20260109.dist-info/licenses/LICENSE
types_jsonschema-4.26.0.20260109.dist-info/METADATA
types_jsonschema-4.26.0.20260109.dist-info/WHEEL
types_jsonschema-4.26.0.20260109.dist-info/top_level.txt
types_jsonschema-4.26.0.20260109.dist-info/RECORD
