Metadata-Version: 2.4
Name: types-jsonschema
Version: 4.26.0.20260109
Summary: Typing stubs for jsonschema
License-Expression: Apache-2.0
Project-URL: Homepage, https://github.com/python/typeshed
Project-URL: GitHub, https://github.com/python/typeshed
Project-URL: Changes, https://github.com/typeshed-internal/stub_uploader/blob/main/data/changelogs/jsonschema.md
Project-URL: Issue tracker, https://github.com/python/typeshed/issues
Project-URL: Chat, https://gitter.im/python/typing
Classifier: Programming Language :: Python :: 3
Classifier: Typing :: Stubs Only
Requires-Python: >=3.9
License-File: LICENSE
Requires-Dist: referencing
Dynamic: license-file
